MANIFEST.in
README.txt
setup.py
sffj-echo.ini
xplecho.py
expel.apps.echo.egg-info/PKG-INFO
expel.apps.echo.egg-info/SOURCES.txt
expel.apps.echo.egg-info/dependency_links.txt
expel.apps.echo.egg-info/requires.txt
expel.apps.echo.egg-info/top_level.txt