Metadata-Version: 1.0
Name: expel.apps.echo
Version: 0.1
Summary: xPL Echo - Echos all messages received from the xPL hub.
Home-page: http://www.sffjunkie.co.uk/python-expel.html#echo
Author: Simon Kennedy
Author-email: code@sffjunkie.co.uk
License: Apache-2.0
Platform: UNKNOWN
